tdc101/__init__.py
tdc101/tdc101.py
tdc101-1.0.0.data/data/tdc101/Problema de rede.mp3
tdc101-1.0.0.dist-info/METADATA
tdc101-1.0.0.dist-info/RECORD
tdc101-1.0.0.dist-info/WHEEL
tdc101-1.0.0.dist-info/top_level.txt
