Metadata-Version: 2.1
Name: tdc101
Version: 1.0.0
Summary: Teste de narração
Home-page: UNKNOWN
Author: Klinsman Jorge
Author-email: UNKNOWN
License: MIT
Platform: UNKNOWN
Classifier: License :: OSI Approved :: MIT License
Classifier: Programming Language :: Python :: 3.4
Classifier: Programming Language :: Python :: 3.5
Classifier: Programming Language :: Python :: 3.6
Requires-Dist: python-vlc
